AegosIN
