Metadata-Version: 2.1
Name: AegosIN
Version: 0.2
Summary: Giting info for any account in the tiktok
Author: AegosIN
Author-email: syakkml@gmail.com
Classifier: Programming Language :: Python :: 3
Classifier: Operating System :: OS Independent
Classifier: License :: OSI Approved :: MIT License
